{
  "th_bundle_config_version": "v1.0.24",
  "translateth": "",

  "translatethcatali_wait_message": "[#FFFF99]กรุณารอการเกิดใหม่ครั้งถัดไป.",
  "translatethcatali_played_message": "[#FF6666]คุณได้เล่นแล้ว.",
  "translatethcatali_no_more_team": "[#FF6666]ไม่มีทีมเพิ่มเติม.",
  "translatethcatali_no_more_spawn": "[#FF6666]ไม่มีจุดเกิดเพิ่มเติม.",
  "translatethcatali_not_enough_upgrade": "[#FF6666]การอัปเกรดไม่เพียงพอ.",
  "translatethcatali_not_leader": "[#FF6666]คุณไม่ใช่หัวหน้าทีม.",
  "translatethcatali_already_playing_waiting": "[#FFFF99]คุณกำลังเล่นหรือรออยู่แล้ว.",
  "translatethcatali_no_team_available": "[#FF6666]ไม่มีทีมให้เข้าร่วม.",
  "translatethcatali_not_a_team_leader": "[#FF6666]คุณไม่ใช่หัวหน้าทีม.",
  "translatethcatali_team_join_request": "[#FFFF99]ทีมของคุณมีคำขอเข้าร่วมจาก[] ",
  "translatethcatali_team_join_instructions": "[#FFFF99]ยอมรับด้วย [#66FF66]\"/accept\"[] หรือปฏิเสธด้วย [#FF6666]\"/deny\".",

  "translatethcatali_common_upgrade_title": "-- [#66CCFF]เมนูอัปเกรด[] --",
  "translatethcatali_common_upgrade_message": "[#66CCFF]เลือกการอัปเกรด:",
  "translatethcatali_common_upgrade_max_hp": "+ [#66FF66]@%[] HP สูงสุด",
  "translatethcatali_common_upgrade_damage": "+ [#FF6666]@%[] ความเสียหาย",
  "translatethcatali_common_upgrade_healing": "+ [#66CCFF]@ HP/s[] การรักษา",
  "translatethcatali_upgrade_unit_final_tier": "[#FFFF99]หน่วยของคุณอยู่ในระดับสุดท้ายแล้ว.",
  "translatethcatali_no_upgrade_available": "[#FF6666]ไม่มีการอัปเกรดสำหรับหน่วยนี้.",
  "translatethcatali_unit_destroyed_upgrade": "[#FF6666]หน่วยของคุณถูกทำลาย. ไม่สามารถอัปเกรดได้.",
  "translatethcatali_choose_next_upgrade_title": "--- [#66CCFF]เลือกการอัปเกรดถัดไป[] ---",
  "translatethcatali_choose_next_upgrade_message": "[#66CCFF]เลือกหน่วยเพื่ออัปเกรด",
  "translatethcatali_pick_next_upgrade_title": "--- [#66CCFF]เลือกหน่วยสำหรับการอัปเกรด[] ---",
  "translatethcatali_pick_next_upgrade_message": "[#66CCFF]กรุณาเลือกหน่วยสำหรับการอัปเกรด",
  "translatethcatali_rare_upgrade_title": "-- [#66CCFF]เมนูอัปเกรดหายาก[] --",
  "translatethcatali_rare_upgrade_message": "เลือกการอัปเกรด [#66CCFF]หายาก[] เพื่ออัปเกรด",
  "translatethcatali_rare_upgrade_unit": "+1 หน่วยสำหรับทีมของคุณ ([#66FF66]poly[])",
  "translatethcatali_rare_upgrade_tier": "[#66CCFF]อัปเกรดหน่วยเฉพาะไปยังระดับถัดไป",
  "translatethcatali_rare_upgrade_special": "[#FF6666]สร้างความเสียหาย 8000 AOE[] ในรัศมี 40 บล็อกและ [#66FF66]รักษาหน่วยทั้งหมด[] ในทีม",
  "translatethcatali_rare_upgrade_buff": "[#66CCFF]เพิ่มสถานะ[] ให้กับหน่วยระดับสุดท้ายเฉพาะ",
  "translatethcatali_pick_next_buff_title": "--- [#66CCFF]เลือกเอฟเฟกต์ที่จะใช้[] ---",
  "translatethcatali_pick_next_buff_message": "[#66CCFF]กรุณาเลือกเอฟเฟกต์ที่จะใช้.\nหมายเหตุ: หากหน่วยตาย, คุณจะสูญเสียเอฟเฟกต์นี้.",
  "translatethcatali_choose_next_buff_title": "--- [#66CCFF]เลือกหน่วยที่จะใช้[] ---",
  "translatethcatali_choose_next_buff_message": "[#66CCFF]เลือกหน่วยที่จะใช้",
  "translatethcatali_effect_applied": "[#FFFF99]หน่วยของคุณมีเอฟเฟกต์นี้อยู่แล้ว.",
  "translatethcatali_upgrade_amount_title": "--- [#66CCFF]ป้อนจำนวน[] ---",
  "translatethcatali_upgrade_amount_message": "[#66CCFF]ป้อนจำนวนที่จะอัปเกรด (1 -> @)",
  "translatethcatali_upgrade_amount_error": "[#FF6666]จำนวนไม่ถูกต้อง. กรุณาป้อนจำนวนที่ถูกต้อง.",

  "translatethcatali_play_note": "\n[#FFFF99]หมายเหตุ[]: [#66FF66]Oct[] และ [#66FF66]Aegires[] ได้รับ [#66CCFF]40xp[] ต่อวินาที.\nคุณสามารถ [#66CCFF]เปลี่ยนโหมดการดูภาษา[] ปัจจุบันโดย [#66FF66]\"/language c\"[] คำสั่ง.",
  "translatethcatali_team_stat": "-- [#66CCFF]สถิติทีมของคุณ[] --\n[#FF9999]HP สูงสุด: []+ %d%%\n[#FF99CC]ความเสียหาย: []+ %d%%\n[#99FFFF]การรักษา: []+ %d/s",
  "translatethcatali_team_upgrade": "\nพิมพ์ \"[#66FF66]/upgrade[]\" เพื่อใช้อัปเกรด\nทั่วไป:  %d, หายาก:  %d",
  "translatethcatali_unit_destroyed": "[]@ [white]ได้สังหาร @ จากทีม @",
  "translatethcatali_unit_low_health": "หน่วย [#66FF66]@[] ของคุณมี [#FF6666]สุขภาพต่ำ[]",
  "translatethcatali_respawn_title": "--- [#66CCFF]การเกิดใหม่กำลังมา[] ---\n",
  "translatethcatali_respawn_message": "@ @: [#66CCFF]@[]\n",
  "translatethcatali_next_catch": "การจับหน่วยถัดไป: [#66CCFF]@[]\n",
  "translatethcatali_time_played": "เวลาที่เล่น: %02d:%02d:%02d\n",

  "translatethcatali_join_title": "--- [#66CCFF]เข้าร่วมทีม[] ---",
  "translatethcatali_join_message": "[#66CCFF]เลือกทีมที่จะเข้าร่วม:",
  "translatethcatali_wait_refresh": "[#FFFF99]กรุณารอ @[] เพื่อเกิดใหม่",
  "translatethcatali_unit_respawn_message": "[#66CCFF]พิมพ์ [#66FF66]\"/play\"[] เพื่อเกิดใหม่[]\n",

  "translatethcatali_welcome_title": "[#FFFF99]ยินดีต้อนรับสู่ Catali.io[]",
  "translatethcatali_welcome_message": "[#66CCFF]คุณต้องการเล่นหรือไม่?[]\n\n",
  "translatethcatali_game_owner": "\n[#66CCFF]เจ้าของ[]: [#FF99CC]<meo>[] neko-chan",
  "translatethcatali_game_contributor": "\n[#66CCFF]ผู้สนับสนุน[]: [#99CCFF]JHM[] และ [#99CCFF]SITUVNgcd.",
  "translatethcatali_button_play": "[#66FF66]เล่น[]",
  "translatethcatali_button_join": "[#FFFF99]เข้าร่วมคนอื่น[]",
  "translatethcatali_button_help": "[#66CCFF]เปิดความช่วยเหลือ[]",

  "translatethcatali_destroy_toast": "[#FF6666]ทีม []@ [white]ถูกกำจัด[]",
  "translatethcatali_leaderboard_header": "\n--- [#FFD700]กระดานผู้นำ[] ---",
  "translatethcatali_level_up_toast": "[#FFD700]เลเวลอัพ![]",
  "translatethcatali_team_level": "[#66FF66]ระดับ []%d\n%s\n%d/%d\n%.2f%%",
  "translatethcatali_gameover_title": "--- [#FF6666]เกมจบ[] ---",
  "translatethcatali_gameover_message": "[#FFFF99]เกมจบ. กรุณารอจนกว่าจะเกิดใหม่ครั้งถัดไป."
}